wandb_offline_sync/__init__.py
wandb_offline_sync/agent/__init__.py
wandb_offline_sync/agent/wandb_sync_agent.py
wandb_offline_sync/farm/__init__.py
wandb_offline_sync/farm/wandb_sync_farm.py
wandb_offline_sync/farm/templates/index.html
wandb_offline_sync-0.0.14.dist-info/LICENSE.txt
wandb_offline_sync-0.0.14.dist-info/METADATA
wandb_offline_sync-0.0.14.dist-info/WHEEL
wandb_offline_sync-0.0.14.dist-info/entry_points.txt
wandb_offline_sync-0.0.14.dist-info/top_level.txt
wandb_offline_sync-0.0.14.dist-info/RECORD
