Metadata-Version: 2.1
Name: wandb-offline-sync
Version: 0.0.14
Summary: Continuously sync offline wandb runs
Author-email: Martin Menabue <martinmnb@live.it>
License: Copyright (c) 2023 WandbOfflineSync
Project-URL: Homepage, https://github.com/MartinMenabue/WandbOfflineSync
Project-URL: Bug Tracker, https://github.com/MartinMenabue/WandbOfflineSync/issues
Keywords: wandb,offline,sync
Classifier: Programming Language :: Python :: 3
Classifier: License :: OSI Approved :: MIT License
Classifier: Operating System :: OS Independent
Requires-Python: >=3.7
License-File: LICENSE.txt
Requires-Dist: Flask
Requires-Dist: requests
Requires-Dist: wandb
